ctf_announcement/__init__.py
ctf_announcement/__main__.py
ctf_announcement-0.3.dist-info/METADATA
ctf_announcement-0.3.dist-info/RECORD
ctf_announcement-0.3.dist-info/WHEEL
ctf_announcement-0.3.dist-info/entry_points.txt
ctf_announcement-0.3.dist-info/top_level.txt
