Metadata-Version: 2.1
Name: ctf-announcement
Version: 0.3
Summary: Fill a CTF announcement template with data from CTFtime
Home-page: https://github.com/secse-ctf/announcement
Author: numirias
Author-email: numirias@users.noreply.github.com
License: MIT
Platform: UNKNOWN
Classifier: Development Status :: 4 - Beta
Classifier: License :: OSI Approved :: MIT License
Classifier: Programming Language :: Python
Classifier: Programming Language :: Python :: 3
Classifier: Programming Language :: Python :: 3.5
Classifier: Programming Language :: Python :: 3.6
Classifier: Programming Language :: Python :: 3.7
Requires-Python: >=3.5
Requires-Dist: python-dateutil
Requires-Dist: feedparser
